Build_Python_To_exe_for_Clung/__init__.py
Build_Python_To_exe_for_Clung/app.py
Build_Python_To_exe_for_Clung/Web/main.html
Build_Python_To_exe_for_Clung/Web/css/main.css
Build_Python_To_exe_for_Clung/Web/js/bootstrap.min.css
Build_Python_To_exe_for_Clung/Web/js/bootstrap.min.js
Build_Python_To_exe_for_Clung/Web/js/jquery-3.6.3.min.js
Build_Python_To_exe_for_Clung/Web/js/popper.min.js
Build_Python_To_exe_for_Clung/Web/js/vue3.global.min.js
Build_Python_To_exe_for_Clung/Web/js/component/app.js
Build_Python_To_exe_for_Clung/python_files/__init__.py
Build_Python_To_exe_for_Clung/python_files/file_dialog.py
py_nui_exe-0.1.0.dist-info/LICENSE
py_nui_exe-0.1.0.dist-info/METADATA
py_nui_exe-0.1.0.dist-info/WHEEL
py_nui_exe-0.1.0.dist-info/entry_points.txt
py_nui_exe-0.1.0.dist-info/top_level.txt
py_nui_exe-0.1.0.dist-info/RECORD
