Metadata-Version: 2.1
Name: py_nui_exe
Version: 0.1.0
Summary: python→exe setup build support tool
Home-page: https://github.com/KMASTERgit/py_nui_exe
Author: CKM
License-File: LICENSE
Requires-Dist: eel>=0.18.1
Requires-Dist: nuitka>=2.5.7
